bmde/__init__.py
bmde/__main__.py
bmde/api.py
bmde/cli.py
bmde/commands/__init__.py
bmde/commands/build/__init__.py
bmde/commands/build/cli.py
bmde/commands/build/command.py
bmde/commands/build/service.py
bmde/commands/build/settings.py
bmde/commands/build/spec.py
bmde/commands/build/backends/__init__.py
bmde/commands/build/backends/backend.py
bmde/commands/build/backends/docker.py
bmde/commands/build/backends/host.py
bmde/commands/check/__init__.py
bmde/commands/check/cli.py
bmde/commands/check/command.py
bmde/commands/debug/__init__.py
bmde/commands/debug/cli.py
bmde/commands/debug/command.py
bmde/commands/debug/service.py
bmde/commands/debug/settings.py
bmde/commands/debug/spec.py
bmde/commands/debug/backends/__init__.py
bmde/commands/debug/backends/backend.py
bmde/commands/debug/backends/docker.py
bmde/commands/debug/backends/host.py
bmde/commands/git/__init__.py
bmde/commands/git/cli.py
bmde/commands/git/command.py
bmde/commands/git/service.py
bmde/commands/git/settings.py
bmde/commands/git/spec.py
bmde/commands/git/backends/__init__.py
bmde/commands/git/backends/backend.py
bmde/commands/git/backends/docker.py
bmde/commands/git/backends/host.py
bmde/commands/patch/__init__.py
bmde/commands/patch/cli.py
bmde/commands/patch/command.py
bmde/commands/patch/service.py
bmde/commands/patch/settings.py
bmde/commands/patch/spec.py
bmde/commands/patch/backends/__init__.py
bmde/commands/patch/backends/backend.py
bmde/commands/patch/backends/docker.py
bmde/commands/patch/backends/host.py
bmde/commands/run/__init__.py
bmde/commands/run/cli.py
bmde/commands/run/command.py
bmde/commands/run/service.py
bmde/commands/run/settings.py
bmde/commands/run/spec.py
bmde/commands/run/backends/__init__.py
bmde/commands/run/backends/backend.py
bmde/commands/run/backends/docker.py
bmde/commands/run/backends/flatpak.py
bmde/commands/run/backends/host.py
bmde/config/__init__.py
bmde/config/command_settings.py
bmde/config/loader.py
bmde/config/logging_settings.py
bmde/config/schema.py
bmde-1.8.0.dist-info/METADATA
bmde-1.8.0.dist-info/WHEEL
bmde-1.8.0.dist-info/entry_points.txt
bmde-1.8.0.dist-info/licenses/LICENSE
bmde-1.8.0.dist-info/RECORD
