Metadata-Version: 2.4
Name: bmde
Version: 1.8.0
Summary: Bare Metal Development Environment CLI; for NDS development for the practical exercises of Computers
Author: AleixMT
License: GPL-3.0-or-later
License-File: LICENSE
Requires-Python: >=3.11
Requires-Dist: pydantic-settings
Requires-Dist: pydantic>=2.0.0
Requires-Dist: rich>=13.0.0
Requires-Dist: rtoml
Requires-Dist: typer>=0.9.0
Provides-Extra: dev
Requires-Dist: black; extra == 'dev'
Requires-Dist: build; extra == 'dev'
Requires-Dist: hatch-vcs; extra == 'dev'
Requires-Dist: hatchling; extra == 'dev'
Requires-Dist: mkdocs-autorefs; extra == 'dev'
Requires-Dist: mkdocs-awesome-pages-plugin; extra == 'dev'
Requires-Dist: mkdocs-material; extra == 'dev'
Requires-Dist: mkdocs-material>=9.0.0; extra == 'dev'
Requires-Dist: mkdocs-typer; extra == 'dev'
Requires-Dist: mkdocs-typer2; extra == 'dev'
Requires-Dist: mkdocs>=1.5.0; extra == 'dev'
Requires-Dist: mkdocstrings[python]; extra == 'dev'
Requires-Dist: mypy; extra == 'dev'
Requires-Dist: pre-commit; extra == 'dev'
Requires-Dist: pymdown-extensions>=10.0; extra == 'dev'
Requires-Dist: pytest; extra == 'dev'
Requires-Dist: ruff; extra == 'dev'
